whatchamacallit/__init__.py
whatchamacallit/fastapi.py
whatchamacallit/flask.py
whatchamacallit/make.py
whatchamacallit/test_make.py
whatchamacallit/examples/__init__.py
whatchamacallit/examples/fastapi_server.py
whatchamacallit/examples/flask_server.py
whatchamacallit-0.0.6.dist-info/LICENSE
whatchamacallit-0.0.6.dist-info/METADATA
whatchamacallit-0.0.6.dist-info/WHEEL
whatchamacallit-0.0.6.dist-info/top_level.txt
whatchamacallit-0.0.6.dist-info/RECORD
