Metadata-Version: 2.1
Name: whatchamacallit
Version: 0.0.6
Summary: Use web resources the pythonic way, import JavaScript modules like you do with Python modules.
Home-page: https://github.com/decatur/whatchamacallit
Author: Wolfgang Kühn
Maintainer: Wolfgang Kühn
License: UNKNOWN
Platform: UNKNOWN
Requires-Python: >=3.6,<4.0
Requires-Dist: importlib-resources (<4.0,>=3.0) ; python_version < "3.9"
